opass/Tolls.json
opass/__init__.py
opass/opass.py
opass/toll.png
opass/workdays.py
opass-1.0.6.dist-info/LICENSE
opass-1.0.6.dist-info/METADATA
opass-1.0.6.dist-info/WHEEL
opass-1.0.6.dist-info/entry_points.txt
opass-1.0.6.dist-info/top_level.txt
opass-1.0.6.dist-info/RECORD
