Metadata-Version: 2.1
Name: opass
Version: 1.0.6
Summary: Calculate toll costs in Olympia Odos
Home-page: https://github.com/panosdim/opass
Author: Panagiotis Dimopoulos
Author-email: panosdim@gmail.com
License: UNKNOWN
Platform: UNKNOWN
Classifier: Programming Language :: Python :: 3
Classifier: License :: OSI Approved :: MIT License
Classifier: Operating System :: OS Independent
Requires-Dist: ttkthemes
Requires-Dist: Pillow
Requires-Dist: numpy
